{
  "simplified": "一瓶子不响，半瓶子晃荡",
  "simplified_stroke_count": 0,
  "details": [
    {
      "pronunciation": [
        {
          "pinyin": " yī píng zi bù xiǎng , bàn píng zi huàng dang",
          "wade_giles_pinyin": "yi1 ping2 zi5 bu4 xiang3 , ban4 ping2 zi5 huang4 dang5"
        }
      ],
      "simplified": "一瓶子不响，半瓶子晃荡",
      "simplified_stroke_count": 0,
      "traditional": "一瓶子不響，半瓶子晃蕩",
      "traditional_stroke_count": 0,
      "meanings": [
        {
          "context": "literature",
          "lexical_item": "idiom",
          "value": "lit. a full bottle makes no sound; a half-filled bottle sloshes"
        },
        {
          "context": "",
          "lexical_item": "",
          "value": "fig. empty vessels make the most noise"
        }
      ],
      "classifiers": [],
      "tags": []
    }
  ]
}