{
  "simplified": "丁丁",
  "details": [
    {
      "pronunciation": [
        {
          "pinyin": "dīng dīng",
          "wade_giles_pinyin": "Ding1 ding1"
        }
      ],
      "simplified": "丁丁",
      "traditional": "丁丁",
      "meanings": [
        {
          "value": "Tintin, cartoon character"
        }
      ],
      "classifiers": [],
      "tags": []
    },
    {
      "pronunciation": [
        {
          "pinyin": "zhēng zhēng",
          "wade_giles_pinyin": "zheng1 zheng1"
        }
      ],
      "simplified": "丁丁",
      "traditional": "丁丁",
      "meanings": [
        {
          "value": "sound of chopping wood, chess pieces hitting the board etc"
        }
      ],
      "classifiers": [],
      "tags": []
    }
  ]
}