{
  "simplified": "久负盛名",
  "details": [
    {
      "pronunciation": [
        {
          "pinyin": "jiǔ fù shèng míng",
          "wade_giles_pinyin": "jiu3 fu4 sheng4 ming2"
        }
      ],
      "simplified": "久负盛名",
      "traditional": "久負盛名",
      "meanings": [
        {
          "value": "seasoned"
        },
        {
          "value": "honed to perfection over centuries"
        },
        {
          "value": "special reserve"
        }
      ],
      "classifiers": [],
      "tags": []
    }
  ]
}