{
  "simplified": "人道",
  "details": [
    {
      "pronunciation": [
        {
          "pinyin": "rén dào",
          "wade_giles_pinyin": "ren2 dao4"
        }
      ],
      "simplified": "人道",
      "traditional": "人道",
      "meanings": [
        {
          "value": "human sympathy"
        },
        {
          "value": "humanitarianism"
        },
        {
          "value": "humane"
        },
        {
          "value": "the \"human way\", one of the stages in the cycle of reincarnation (Buddhism)"
        },
        {
          "value": "sexual intercourse"
        }
      ],
      "classifiers": [],
      "tags": []
    }
  ]
}