{
  "simplified": "仙药",
  "details": [
    {
      "pronunciation": [
        {
          "pinyin": "xiān yào",
          "wade_giles_pinyin": "xian1 yao4"
        }
      ],
      "simplified": "仙药",
      "traditional": "仙藥",
      "meanings": [
        {
          "value": "legendary magic potion of immortals"
        },
        {
          "value": "panacea"
        },
        {
          "value": "fig. wonder solution to a problem"
        }
      ],
      "classifiers": [],
      "tags": []
    }
  ]
}