{
  "simplified": "公犬",
  "simplified_stroke_count": 0,
  "details": [
    {
      "pronunciation": [
        {
          "pinyin": " gōng quǎn",
          "wade_giles_pinyin": "gong1 quan3"
        }
      ],
      "simplified": "公犬",
      "simplified_stroke_count": 0,
      "traditional": "公犬",
      "traditional_stroke_count": 0,
      "meanings": [
        {
          "context": "",
          "lexical_item": "",
          "value": "male dog"
        }
      ],
      "classifiers": [],
      "tags": []
    }
  ]
}