{
  "simplified": "再制盐",
  "simplified_stroke_count": 0,
  "details": [
    {
      "pronunciation": [
        {
          "pinyin": " zài zhì yán",
          "wade_giles_pinyin": "zai4 zhi4 yan2"
        }
      ],
      "simplified": "再制盐",
      "simplified_stroke_count": 0,
      "traditional": "再製鹽",
      "traditional_stroke_count": 0,
      "meanings": [
        {
          "context": "",
          "lexical_item": "",
          "value": "refined salt"
        }
      ],
      "classifiers": [],
      "tags": []
    }
  ]
}