{
  "simplified": "刚刚",
  "simplified_stroke_count": 0,
  "details": [
    {
      "pronunciation": [
        {
          "pinyin": " gāng gang",
          "wade_giles_pinyin": "gang1 gang5"
        }
      ],
      "simplified": "刚刚",
      "simplified_stroke_count": 0,
      "traditional": "剛剛",
      "traditional_stroke_count": 0,
      "meanings": [
        {
          "context": "",
          "lexical_item": "",
          "value": "just recently"
        },
        {
          "context": "",
          "lexical_item": "",
          "value": "just a moment ago"
        }
      ],
      "classifiers": [],
      "tags": [
        "adverb"
      ]
    }
  ]
}