{
  "simplified": "前半天儿",
  "details": [
    {
      "pronunciation": [
        {
          "pinyin": "qián bàn tiān r",
          "wade_giles_pinyin": "qian2 ban4 tian1 r5"
        }
      ],
      "simplified": "前半天儿",
      "traditional": "前半天兒",
      "meanings": [
        {
          "context": "variant",
          "value": "erhua variant of 前半天[qian2 ban4 tian1]",
          "simplified": "e",
          "traditional": "rhua  前半天",
          "wade_giles_pinyin": "qian2 ban4 tian1"
        }
      ],
      "classifiers": [],
      "tags": []
    }
  ]
}