{
  "simplified": "北竿乡",
  "simplified_stroke_count": 0,
  "details": [
    {
      "pronunciation": [
        {
          "pinyin": " běi gān xiāng",
          "wade_giles_pinyin": "Bei3 gan1 xiang1"
        }
      ],
      "simplified": "北竿乡",
      "simplified_stroke_count": 0,
      "traditional": "北竿鄉",
      "traditional_stroke_count": 0,
      "meanings": [
        {
          "context": "",
          "lexical_item": "",
          "value": "Peikan township in Lienchiang county 連江縣|连江县[Lian2 jiang1 xian4] i.e. the Matsu Islands, Taiwan"
        }
      ],
      "classifiers": [],
      "tags": []
    }
  ]
}