{
  "simplified": "原位",
  "details": [
    {
      "pronunciation": [
        {
          "pinyin": "yuán weì",
          "wade_giles_pinyin": "yuan2 wei4"
        }
      ],
      "simplified": "原位",
      "traditional": "原位",
      "meanings": [
        {
          "value": "original position"
        },
        {
          "value": "(in) the same place"
        },
        {
          "value": "normal position"
        },
        {
          "value": "the place where one currently is"
        },
        {
          "value": "in situ"
        }
      ],
      "classifiers": [],
      "tags": []
    }
  ]
}