{
  "simplified": "同一挂",
  "details": [
    {
      "pronunciation": [
        {
          "pinyin": "tóng yī guà",
          "wade_giles_pinyin": "tong2 yi1 gua4"
        }
      ],
      "simplified": "同一挂",
      "traditional": "同一掛",
      "meanings": [
        {
          "context": "colloquial",
          "value": "to have a lot in common (with sb)"
        },
        {
          "value": "to get along well with each other"
        }
      ],
      "classifiers": [],
      "tags": [
        "verb"
      ]
    }
  ]
}