{
  "simplified": "听墙根儿",
  "simplified_stroke_count": 0,
  "details": [
    {
      "pronunciation": [
        {
          "pinyin": " tīng qiáng gēn r",
          "wade_giles_pinyin": "ting1 qiang2 gen1 r5"
        }
      ],
      "simplified": "听墙根儿",
      "simplified_stroke_count": 0,
      "traditional": "聽牆根兒",
      "traditional_stroke_count": 0,
      "meanings": [
        {
          "context": "variant",
          "lexical_item": "",
          "value": "erhua  聽牆根|听墙根[ting1 qiang2 gen1]"
        }
      ],
      "classifiers": [],
      "tags": []
    }
  ]
}