{
  "simplified": "听错",
  "simplified_stroke_count": 0,
  "details": [
    {
      "pronunciation": [
        {
          "pinyin": " tīng cuò",
          "wade_giles_pinyin": "ting1 cuo4"
        }
      ],
      "simplified": "听错",
      "simplified_stroke_count": 0,
      "traditional": "聽錯",
      "traditional_stroke_count": 0,
      "meanings": [
        {
          "context": "",
          "lexical_item": "",
          "value": "to mishear"
        }
      ],
      "classifiers": [],
      "tags": [
        "verb"
      ]
    }
  ]
}