{
  "simplified": "哥本哈根",
  "simplified_stroke_count": 0,
  "details": [
    {
      "pronunciation": [
        {
          "pinyin": " gē běn hā gēn",
          "wade_giles_pinyin": "Ge1 ben3 ha1 gen1"
        }
      ],
      "simplified": "哥本哈根",
      "simplified_stroke_count": 0,
      "traditional": "哥本哈根",
      "traditional_stroke_count": 0,
      "meanings": [
        {
          "context": "",
          "lexical_item": "",
          "value": "Copenhagen or København, capital of Denmark"
        }
      ],
      "classifiers": [],
      "tags": []
    }
  ]
}