{
  "simplified": "唱对台戏",
  "simplified_stroke_count": null,
  "details": [
    {
      "pronunciation": [
        {
          "pinyin": "chàng duì tái xì",
          "wade_giles_pinyin": "chang4 dui4 tai2 xi4"
        }
      ],
      "simplified": "唱对台戏",
      "simplified_stroke_count": null,
      "traditional": "唱對臺戲",
      "traditional_stroke_count": null,
      "meanings": [
        {
          "context": null,
          "lexical_item": "idiom",
          "value": "to put on a rival show ; to set oneself up against sb"
        },
        {
          "context": null,
          "lexical_item": null,
          "value": "to get into confrontation"
        }
      ],
      "classifiers": [],
      "tags": [
        "verb"
      ]
    }
  ]
}