{
  "simplified": "啻",
  "simplified_stroke_count": 12,
  "details": [
    {
      "pronunciation": [
        {
          "pinyin": "chì",
          "wade_giles_pinyin": "chi4"
        }
      ],
      "simplified": "啻",
      "simplified_stroke_count": 12,
      "traditional": "啻",
      "traditional_stroke_count": 12,
      "meanings": [
        {
          "value": "only (classical, usually follows negative or question words)"
        },
        {
          "value": "(not) just"
        }
      ],
      "classifiers": [],
      "tags": []
    }
  ]
}