{
  "simplified": "圣索非亚",
  "simplified_stroke_count": 0,
  "details": [
    {
      "pronunciation": [
        {
          "pinyin": " shèng suǒ fēi yà",
          "wade_giles_pinyin": "Sheng4 suo3 fei1 ya4"
        }
      ],
      "simplified": "圣索非亚",
      "simplified_stroke_count": 0,
      "traditional": "聖索非亞",
      "traditional_stroke_count": 0,
      "meanings": [
        {
          "context": "",
          "lexical_item": "",
          "value": "Hagia Sophia (Greek: Holy wisdom)"
        }
      ],
      "classifiers": [],
      "tags": []
    }
  ]
}