{
  "simplified": "壁报",
  "simplified_stroke_count": null,
  "details": [
    {
      "pronunciation": [
        {
          "pinyin": "bì bào",
          "wade_giles_pinyin": "bi4 bao4"
        }
      ],
      "simplified": "壁报",
      "simplified_stroke_count": null,
      "traditional": "壁報",
      "traditional_stroke_count": null,
      "meanings": [
        {
          "context": null,
          "lexical_item": null,
          "value": "wall newspaper"
        }
      ],
      "classifiers": [],
      "tags": []
    }
  ]
}