{
  "simplified": "夸海口",
  "simplified_stroke_count": 0,
  "details": [
    {
      "pronunciation": [
        {
          "pinyin": " kuā hǎi kǒu",
          "wade_giles_pinyin": "kua1 hai3 kou3"
        }
      ],
      "simplified": "夸海口",
      "simplified_stroke_count": 0,
      "traditional": "誇海口",
      "traditional_stroke_count": 0,
      "meanings": [
        {
          "context": "",
          "lexical_item": "",
          "value": "to boast"
        },
        {
          "context": "",
          "lexical_item": "",
          "value": "to talk big"
        }
      ],
      "classifiers": [],
      "tags": [
        "verb"
      ]
    }
  ]
}