{
  "simplified": "客",
  "simplified_stroke_count": 9,
  "details": [
    {
      "pronunciation": [
        {
          "pinyin": "kè",
          "wade_giles_pinyin": "ke4"
        }
      ],
      "simplified": "客",
      "simplified_stroke_count": 9,
      "traditional": "客",
      "traditional_stroke_count": 9,
      "meanings": [
        {
          "value": "customer"
        },
        {
          "value": "visitor"
        },
        {
          "value": "guest"
        }
      ],
      "classifiers": [],
      "tags": []
    }
  ]
}