{
  "simplified": "容器",
  "simplified_stroke_count": 0,
  "details": [
    {
      "pronunciation": [
        {
          "pinyin": " róng qì",
          "wade_giles_pinyin": "rong2 qi4"
        }
      ],
      "simplified": "容器",
      "simplified_stroke_count": 0,
      "traditional": "容器",
      "traditional_stroke_count": 0,
      "meanings": [
        {
          "context": "",
          "lexical_item": "",
          "value": "receptacle"
        },
        {
          "context": "",
          "lexical_item": "",
          "value": "vessel"
        },
        {
          "context": "",
          "lexical_item": "",
          "value": "(computing) container"
        }
      ],
      "classifiers": [],
      "tags": []
    }
  ]
}