{
  "simplified": "密文",
  "simplified_stroke_count": null,
  "details": [
    {
      "pronunciation": [
        {
          "pinyin": "mì wén",
          "wade_giles_pinyin": "mi4 wen2"
        }
      ],
      "simplified": "密文",
      "simplified_stroke_count": null,
      "traditional": "密文",
      "traditional_stroke_count": null,
      "meanings": [
        {
          "context": null,
          "lexical_item": null,
          "value": "coded text"
        },
        {
          "context": null,
          "lexical_item": null,
          "value": "cypher"
        }
      ],
      "classifiers": [],
      "tags": []
    }
  ]
}