{
  "simplified": "富阳",
  "simplified_stroke_count": 0,
  "details": [
    {
      "pronunciation": [
        {
          "pinyin": " fù yáng",
          "wade_giles_pinyin": "Fu4 yang2"
        }
      ],
      "simplified": "富阳",
      "simplified_stroke_count": 0,
      "traditional": "富陽",
      "traditional_stroke_count": 0,
      "meanings": [
        {
          "context": "",
          "lexical_item": "",
          "value": "Fuyang county level city in Hangzhou 杭州[Hang2 zhou1], Zhejiang"
        }
      ],
      "classifiers": [],
      "tags": []
    }
  ]
}