{
  "simplified": "岩屑",
  "simplified_stroke_count": 0,
  "details": [
    {
      "pronunciation": [
        {
          "pinyin": " yán xiè",
          "wade_giles_pinyin": "yan2 xie4"
        }
      ],
      "simplified": "岩屑",
      "simplified_stroke_count": 0,
      "traditional": "岩屑",
      "traditional_stroke_count": 0,
      "meanings": [
        {
          "context": "",
          "lexical_item": "",
          "value": "(rock) debris"
        },
        {
          "context": "",
          "lexical_item": "",
          "value": "scree"
        }
      ],
      "classifiers": [],
      "tags": []
    }
  ]
}