{
  "simplified": "幼年",
  "simplified_stroke_count": null,
  "details": [
    {
      "pronunciation": [
        {
          "pinyin": "yòu nián",
          "wade_giles_pinyin": "you4 nian2"
        }
      ],
      "simplified": "幼年",
      "simplified_stroke_count": null,
      "traditional": "幼年",
      "traditional_stroke_count": null,
      "meanings": [
        {
          "context": null,
          "lexical_item": null,
          "value": "childhood"
        },
        {
          "context": null,
          "lexical_item": null,
          "value": "infancy"
        }
      ],
      "classifiers": [],
      "tags": []
    }
  ]
}