{
  "simplified": "怎么",
  "details": [
    {
      "pronunciation": [
        {
          "pinyin": "zěn me",
          "wade_giles_pinyin": "zen3 me5"
        }
      ],
      "simplified": "怎么",
      "traditional": "怎麼",
      "meanings": [
        {
          "value": "how?"
        },
        {
          "value": "what?"
        },
        {
          "value": "why?"
        }
      ],
      "classifiers": [],
      "tags": []
    },
    {
      "pronunciation": [
        {
          "pinyin": "zěn me",
          "wade_giles_pinyin": "zen3 me5"
        }
      ],
      "simplified": "怎么",
      "traditional": "怎麽",
      "meanings": [
        {
          "context": "variant",
          "value": "variant of 怎麼|怎么[zen3 me5]",
          "simplified": "怎",
          "traditional": "麼|怎么",
          "wade_giles_pinyin": "zen3 me5"
        }
      ],
      "classifiers": [],
      "tags": []
    }
  ]
}