{
  "simplified": "悪",
  "simplified_stroke_count": 11,
  "details": [
    {
      "pronunciation": [
        {
          "pinyin": "è",
          "wade_giles_pinyin": "e4"
        }
      ],
      "simplified": "悪",
      "simplified_stroke_count": 11,
      "traditional": "悪",
      "traditional_stroke_count": 11,
      "meanings": [
        {
          "context": "Japanese",
          "value": "Japanese variant of 惡|恶[e4]"
        }
      ],
      "classifiers": [],
      "tags": []
    }
  ]
}