{
  "simplified": "愯",
  "simplified_stroke_count": 13,
  "details": [
    {
      "pronunciation": [
        {
          "pinyin": "sǒng",
          "wade_giles_pinyin": "song3"
        }
      ],
      "simplified": "愯",
      "simplified_stroke_count": 13,
      "traditional": "愯",
      "traditional_stroke_count": 13,
      "meanings": [
        {
          "context": "old variant",
          "lexical_item": null,
          "value": "悚[song3]"
        }
      ],
      "classifiers": [],
      "tags": []
    }
  ]
}