{
  "simplified": "投硬币",
  "simplified_stroke_count": 0,
  "details": [
    {
      "pronunciation": [
        {
          "pinyin": " tóu yìng bì",
          "wade_giles_pinyin": "tou2 ying4 bi4"
        }
      ],
      "simplified": "投硬币",
      "simplified_stroke_count": 0,
      "traditional": "投硬幣",
      "traditional_stroke_count": 0,
      "meanings": [
        {
          "context": "",
          "lexical_item": "",
          "value": "coin-operated"
        },
        {
          "context": "",
          "lexical_item": "",
          "value": "to insert a coin"
        }
      ],
      "classifiers": [],
      "tags": [
        "verb"
      ]
    }
  ]
}