{
  "simplified": "摆乌龙",
  "simplified_stroke_count": 0,
  "details": [
    {
      "pronunciation": [
        {
          "pinyin": " bǎi wū lóng",
          "wade_giles_pinyin": "bai3 wu1 long2"
        }
      ],
      "simplified": "摆乌龙",
      "simplified_stroke_count": 0,
      "traditional": "擺烏龍",
      "traditional_stroke_count": 0,
      "meanings": [
        {
          "context": "",
          "lexical_item": "",
          "value": "to mess sth up"
        },
        {
          "context": "",
          "lexical_item": "",
          "value": "to screw up"
        }
      ],
      "classifiers": [],
      "tags": [
        "verb"
      ]
    }
  ]
}