{
  "simplified": "斚",
  "simplified_stroke_count": 10,
  "details": [
    {
      "pronunciation": [
        {
          "pinyin": "jiǎ",
          "wade_giles_pinyin": "jia3"
        }
      ],
      "simplified": "斚",
      "simplified_stroke_count": 10,
      "traditional": "斚",
      "traditional_stroke_count": 10,
      "meanings": [
        {
          "context": "variant",
          "value": "variant of 斝[jia3]",
          "simplified": "斝",
          "traditional": "",
          "wade_giles_pinyin": "jia3"
        }
      ],
      "classifiers": [],
      "tags": []
    }
  ]
}