{
  "simplified": "施虐狂",
  "simplified_stroke_count": 0,
  "details": [
    {
      "pronunciation": [
        {
          "pinyin": " shī nüè kuáng",
          "wade_giles_pinyin": "shi1 nu:e4 kuang2"
        }
      ],
      "simplified": "施虐狂",
      "simplified_stroke_count": 0,
      "traditional": "施虐狂",
      "traditional_stroke_count": 0,
      "meanings": [
        {
          "context": "",
          "lexical_item": "",
          "value": "sadism (psychiatry)"
        }
      ],
      "classifiers": [],
      "tags": []
    }
  ]
}