{
  "simplified": "毕节",
  "simplified_stroke_count": 0,
  "details": [
    {
      "pronunciation": [
        {
          "pinyin": " bì jié",
          "wade_giles_pinyin": "Bi4 jie2"
        }
      ],
      "simplified": "毕节",
      "simplified_stroke_count": 0,
      "traditional": "畢節",
      "traditional_stroke_count": 0,
      "meanings": [
        {
          "context": "",
          "lexical_item": "",
          "value": "Bijie city and prefecture in Guizhou"
        }
      ],
      "classifiers": [],
      "tags": []
    }
  ]
}