{
  "simplified": "汇费",
  "simplified_stroke_count": null,
  "details": [
    {
      "pronunciation": [
        {
          "pinyin": "huì feì",
          "wade_giles_pinyin": "hui4 fei4"
        }
      ],
      "simplified": "汇费",
      "simplified_stroke_count": null,
      "traditional": "匯費",
      "traditional_stroke_count": null,
      "meanings": [
        {
          "context": null,
          "lexical_item": null,
          "value": "remittance fee"
        }
      ],
      "classifiers": [],
      "tags": []
    }
  ]
}