{
  "simplified": "海宁",
  "simplified_stroke_count": 0,
  "details": [
    {
      "pronunciation": [
        {
          "pinyin": " hǎi níng",
          "wade_giles_pinyin": "Hai3 ning2"
        }
      ],
      "simplified": "海宁",
      "simplified_stroke_count": 0,
      "traditional": "海寧",
      "traditional_stroke_count": 0,
      "meanings": [
        {
          "context": "",
          "lexical_item": "",
          "value": "Haining county level city in Jiaxing 嘉興|嘉兴[Jia1 xing1], Zhejiang"
        }
      ],
      "classifiers": [],
      "tags": []
    }
  ]
}