{
  "simplified": "用心",
  "simplified_stroke_count": null,
  "details": [
    {
      "pronunciation": [
        {
          "pinyin": "yòng xīn",
          "wade_giles_pinyin": "yong4 xin1"
        }
      ],
      "simplified": "用心",
      "simplified_stroke_count": null,
      "traditional": "用心",
      "traditional_stroke_count": null,
      "meanings": [
        {
          "context": null,
          "lexical_item": null,
          "value": "motive"
        },
        {
          "context": null,
          "lexical_item": null,
          "value": "intention"
        },
        {
          "context": null,
          "lexical_item": null,
          "value": "to be diligent or attentive"
        },
        {
          "context": null,
          "lexical_item": null,
          "value": "careful"
        }
      ],
      "classifiers": [],
      "tags": [
        "verb"
      ]
    }
  ]
}