{
  "simplified": "知了",
  "simplified_stroke_count": null,
  "details": [
    {
      "pronunciation": [
        {
          "pinyin": "zhī liǎo",
          "wade_giles_pinyin": "zhi1 liao3"
        }
      ],
      "simplified": "知了",
      "simplified_stroke_count": null,
      "traditional": "知了",
      "traditional_stroke_count": null,
      "meanings": [
        {
          "context": null,
          "lexical_item": null,
          "value": "cicada (onom.)"
        }
      ],
      "classifiers": [],
      "tags": []
    }
  ]
}