{
  "simplified": "秕糠",
  "simplified_stroke_count": 0,
  "details": [
    {
      "pronunciation": [
        {
          "pinyin": " bǐ kāng",
          "wade_giles_pinyin": "bi3 kang1"
        }
      ],
      "simplified": "秕糠",
      "simplified_stroke_count": 0,
      "traditional": "秕糠",
      "traditional_stroke_count": 0,
      "meanings": [
        {
          "context": "",
          "lexical_item": "",
          "value": "chaff"
        },
        {
          "context": "",
          "lexical_item": "",
          "value": "worthless stuff"
        }
      ],
      "classifiers": [],
      "tags": []
    }
  ]
}