{
  "simplified": "粉刺",
  "details": [
    {
      "pronunciation": [
        {
          "pinyin": "fěn cì",
          "wade_giles_pinyin": "fen3 ci4"
        }
      ],
      "simplified": "粉刺",
      "traditional": "粉刺",
      "meanings": [
        {
          "value": "pimple"
        },
        {
          "value": "comedo"
        },
        {
          "value": "blackhead"
        },
        {
          "value": "acne"
        }
      ],
      "classifiers": [],
      "tags": []
    }
  ]
}