{
  "simplified": "缓缓",
  "simplified_stroke_count": 0,
  "details": [
    {
      "pronunciation": [
        {
          "pinyin": " huǎn huǎn",
          "wade_giles_pinyin": "huan3 huan3"
        }
      ],
      "simplified": "缓缓",
      "simplified_stroke_count": 0,
      "traditional": "緩緩",
      "traditional_stroke_count": 0,
      "meanings": [
        {
          "context": "",
          "lexical_item": "",
          "value": "slowly"
        },
        {
          "context": "",
          "lexical_item": "",
          "value": "unhurriedly"
        },
        {
          "context": "",
          "lexical_item": "",
          "value": "little by little"
        }
      ],
      "classifiers": [],
      "tags": []
    }
  ]
}