{
  "simplified": "翦",
  "simplified_stroke_count": 15,
  "details": [
    {
      "pronunciation": [
        {
          "pinyin": " jiǎn",
          "wade_giles_pinyin": "Jian3"
        }
      ],
      "simplified": "翦",
      "simplified_stroke_count": 15,
      "traditional": "翦",
      "traditional_stroke_count": 15,
      "meanings": [
        {
          "context": "",
          "lexical_item": "",
          "value": "surname Jian"
        }
      ],
      "classifiers": [],
      "tags": []
    },
    {
      "pronunciation": [
        {
          "pinyin": " jiǎn",
          "wade_giles_pinyin": "jian3"
        }
      ],
      "simplified": "翦",
      "simplified_stroke_count": 15,
      "traditional": "翦",
      "traditional_stroke_count": 15,
      "meanings": [
        {
          "context": "variant",
          "lexical_item": "",
          "value": "剪[jian3]"
        }
      ],
      "classifiers": [],
      "tags": []
    }
  ]
}