{
  "simplified": "肉感",
  "details": [
    {
      "pronunciation": [
        {
          "pinyin": "ròu gǎn",
          "wade_giles_pinyin": "rou4 gan3"
        }
      ],
      "simplified": "肉感",
      "traditional": "肉感",
      "meanings": [
        {
          "value": "sexiness"
        },
        {
          "value": "sexy"
        },
        {
          "value": "sensuality"
        },
        {
          "value": "sensual"
        },
        {
          "value": "voluptuous"
        }
      ],
      "classifiers": [],
      "tags": []
    }
  ]
}