{
  "simplified": "自",
  "simplified_stroke_count": 6,
  "details": [
    {
      "pronunciation": [
        {
          "pinyin": "zì",
          "wade_giles_pinyin": "zi4"
        }
      ],
      "simplified": "自",
      "simplified_stroke_count": 6,
      "traditional": "自",
      "traditional_stroke_count": 6,
      "meanings": [
        {
          "value": "self"
        },
        {
          "value": "oneself"
        },
        {
          "value": "from"
        },
        {
          "value": "since"
        },
        {
          "value": "naturally"
        },
        {
          "value": "surely"
        }
      ],
      "classifiers": [],
      "tags": []
    }
  ]
}