{
  "simplified": "薄纸",
  "simplified_stroke_count": 0,
  "details": [
    {
      "pronunciation": [
        {
          "pinyin": " báo zhǐ",
          "wade_giles_pinyin": "bao2 zhi3"
        }
      ],
      "simplified": "薄纸",
      "simplified_stroke_count": 0,
      "traditional": "薄紙",
      "traditional_stroke_count": 0,
      "meanings": [
        {
          "context": "",
          "lexical_item": "",
          "value": "thin paper (tissue paper, onionskin etc)"
        }
      ],
      "classifiers": [],
      "tags": []
    }
  ]
}