{
  "simplified": "贝叶棕",
  "simplified_stroke_count": 0,
  "details": [
    {
      "pronunciation": [
        {
          "pinyin": " bèi yè zōng",
          "wade_giles_pinyin": "bei4 ye4 zong1"
        }
      ],
      "simplified": "贝叶棕",
      "simplified_stroke_count": 0,
      "traditional": "貝葉棕",
      "traditional_stroke_count": 0,
      "meanings": [
        {
          "context": "",
          "lexical_item": "",
          "value": "pattra palm tree (Corypha umbraculifera), whose leaves were used as paper substitute for Buddhist sutras"
        }
      ],
      "classifiers": [],
      "tags": []
    }
  ]
}