{
  "simplified": "贫",
  "simplified_stroke_count": 8,
  "details": [
    {
      "pronunciation": [
        {
          "pinyin": " pín",
          "wade_giles_pinyin": "pin2"
        }
      ],
      "simplified": "贫",
      "simplified_stroke_count": 8,
      "traditional": "貧",
      "traditional_stroke_count": 11,
      "meanings": [
        {
          "context": "",
          "lexical_item": "",
          "value": "poor"
        },
        {
          "context": "",
          "lexical_item": "",
          "value": "inadequate"
        },
        {
          "context": "",
          "lexical_item": "",
          "value": "deficient"
        },
        {
          "context": "",
          "lexical_item": "",
          "value": "garrulous"
        }
      ],
      "classifiers": [],
      "tags": []
    }
  ]
}