{
  "simplified": "轧花机",
  "simplified_stroke_count": null,
  "details": [
    {
      "pronunciation": [
        {
          "pinyin": "yà huā jī",
          "wade_giles_pinyin": "ya4 hua1 ji1"
        }
      ],
      "simplified": "轧花机",
      "simplified_stroke_count": null,
      "traditional": "軋花機",
      "traditional_stroke_count": null,
      "meanings": [
        {
          "context": null,
          "lexical_item": null,
          "value": "cotton gin"
        }
      ],
      "classifiers": [],
      "tags": []
    }
  ]
}