{
  "simplified": "转调",
  "details": [
    {
      "pronunciation": [
        {
          "pinyin": "zhuǎn diào",
          "wade_giles_pinyin": "zhuan3 diao4"
        }
      ],
      "simplified": "转调",
      "traditional": "轉調",
      "meanings": [
        {
          "value": "(music) to change key"
        },
        {
          "value": "modulation"
        },
        {
          "value": "(of an employee) to be transferred to another post"
        }
      ],
      "classifiers": [],
      "tags": []
    }
  ]
}