{
  "simplified": "软刀子",
  "details": [
    {
      "pronunciation": [
        {
          "pinyin": "ruǎn dāo zi",
          "wade_giles_pinyin": "ruan3 dao1 zi5"
        }
      ],
      "simplified": "软刀子",
      "traditional": "軟刀子",
      "meanings": [
        {
          "context": "literature",
          "value": "the soft knife"
        },
        {
          "context": "figuratively",
          "value": "underhanded tactics"
        },
        {
          "value": "devious means of attack"
        }
      ],
      "classifiers": [],
      "tags": []
    }
  ]
}