{
  "simplified": "运送",
  "simplified_stroke_count": 0,
  "details": [
    {
      "pronunciation": [
        {
          "pinyin": " yùn sòng",
          "wade_giles_pinyin": "yun4 song4"
        }
      ],
      "simplified": "运送",
      "simplified_stroke_count": 0,
      "traditional": "運送",
      "traditional_stroke_count": 0,
      "meanings": [
        {
          "context": "",
          "lexical_item": "",
          "value": "to transport"
        },
        {
          "context": "",
          "lexical_item": "",
          "value": "to carry"
        }
      ],
      "classifiers": [],
      "tags": [
        "verb"
      ]
    }
  ]
}