{
  "simplified": "这还了得",
  "simplified_stroke_count": 0,
  "details": [
    {
      "pronunciation": [
        {
          "pinyin": " zhè hái liǎo dé",
          "wade_giles_pinyin": "zhe4 hai2 liao3 de2"
        }
      ],
      "simplified": "这还了得",
      "simplified_stroke_count": 0,
      "traditional": "這還了得",
      "traditional_stroke_count": 0,
      "meanings": [
        {
          "context": "",
          "lexical_item": "",
          "value": "How dare you!"
        },
        {
          "context": "",
          "lexical_item": "",
          "value": "This is an outrage!"
        },
        {
          "context": "",
          "lexical_item": "",
          "value": "Absolutely disgraceful!"
        }
      ],
      "classifiers": [],
      "tags": []
    }
  ]
}