{
  "simplified": "酂",
  "simplified_stroke_count": 19,
  "details": [
    {
      "pronunciation": [
        {
          "pinyin": "zàn",
          "wade_giles_pinyin": "zan4"
        }
      ],
      "simplified": "酂",
      "simplified_stroke_count": 19,
      "traditional": "酇",
      "traditional_stroke_count": 22,
      "meanings": [
        {
          "value": "group of 100 families"
        },
        {
          "value": "place name"
        }
      ],
      "classifiers": [],
      "tags": []
    }
  ]
}