{
  "simplified": "钻营",
  "details": [
    {
      "pronunciation": [
        {
          "pinyin": "zuān yíng",
          "wade_giles_pinyin": "zuan1 ying2"
        }
      ],
      "simplified": "钻营",
      "traditional": "鑽營",
      "meanings": [
        {
          "value": "toadying for personal gain"
        },
        {
          "value": "to curry favor"
        },
        {
          "value": "to study in great depth"
        }
      ],
      "classifiers": [],
      "tags": [
        "verb"
      ]
    }
  ]
}