{
  "simplified": "雪雁",
  "simplified_stroke_count": 0,
  "details": [
    {
      "pronunciation": [
        {
          "pinyin": " xuě yàn",
          "wade_giles_pinyin": "xue3 yan4"
        }
      ],
      "simplified": "雪雁",
      "simplified_stroke_count": 0,
      "traditional": "雪雁",
      "traditional_stroke_count": 0,
      "meanings": [
        {
          "context": "",
          "lexical_item": "",
          "value": "(bird species of China) snow goose (Anser caerulescens)"
        }
      ],
      "classifiers": [],
      "tags": []
    }
  ]
}