{
  "simplified": "风口",
  "simplified_stroke_count": 0,
  "details": [
    {
      "pronunciation": [
        {
          "pinyin": " fēng kǒu",
          "wade_giles_pinyin": "feng1 kou3"
        }
      ],
      "simplified": "风口",
      "simplified_stroke_count": 0,
      "traditional": "風口",
      "traditional_stroke_count": 0,
      "meanings": [
        {
          "context": "",
          "lexical_item": "",
          "value": "air vent"
        },
        {
          "context": "",
          "lexical_item": "",
          "value": "drafty place"
        },
        {
          "context": "",
          "lexical_item": "",
          "value": "wind gap (geology)"
        },
        {
          "context": "",
          "lexical_item": "",
          "value": "tuyere (furnace air nozzle)"
        }
      ],
      "classifiers": [],
      "tags": []
    }
  ]
}