{
  "simplified": "香蕉人",
  "simplified_stroke_count": 0,
  "details": [
    {
      "pronunciation": [
        {
          "pinyin": " xiāng jiāo rén",
          "wade_giles_pinyin": "xiang1 jiao1 ren2"
        }
      ],
      "simplified": "香蕉人",
      "simplified_stroke_count": 0,
      "traditional": "香蕉人",
      "traditional_stroke_count": 0,
      "meanings": [
        {
          "context": "",
          "lexical_item": "",
          "value": "banana person (yellow outside, white inside)"
        },
        {
          "context": "",
          "lexical_item": "",
          "value": "mildly pejorative term used by Chinese for assimilated Asian Americans"
        },
        {
          "context": "",
          "lexical_item": "",
          "value": "Westernized person of Asian appearance"
        }
      ],
      "classifiers": [],
      "tags": []
    }
  ]
}