{
  "simplified": "高分辨率",
  "simplified_stroke_count": 0,
  "details": [
    {
      "pronunciation": [
        {
          "pinyin": " gāo fēn biàn lǜ",
          "wade_giles_pinyin": "gao1 fen1 bian4 lu:4"
        }
      ],
      "simplified": "高分辨率",
      "simplified_stroke_count": 0,
      "traditional": "高分辨率",
      "traditional_stroke_count": 0,
      "meanings": [
        {
          "context": "",
          "lexical_item": "",
          "value": "high resolution"
        }
      ],
      "classifiers": [],
      "tags": []
    }
  ]
}