{
  "simplified": "𬙂",
  "simplified_stroke_count": 14,
  "details": [
    {
      "pronunciation": [
        {
          "pinyin": " yǐn",
          "wade_giles_pinyin": "yin3"
        }
      ],
      "simplified": "𬙂",
      "simplified_stroke_count": 14,
      "traditional": "縯",
      "traditional_stroke_count": 17,
      "meanings": [
        {
          "context": "",
          "lexical_item": "",
          "value": "long"
        }
      ],
      "classifiers": [],
      "tags": []
    }
  ]
}